{
  "resolvedId": "E:/lixycode/testcode/node_modules/element-plus/theme-chalk/src/aside.scss",
  "transforms": [
    {
      "name": "__load__",
      "result": "@use 'mixins/mixins' as *;\n\n@include b(aside) {\n  overflow: auto;\n  box-sizing: border-box;\n  flex-shrink: 0;\n  width: var(#{getCssVarName('aside', 'width')}, 300px);\n}\n",
      "start": 1738720225552,
      "end": 1738720225552
    },
    {
      "name": "vite-plugin-vue-inspector",
      "start": 1738720225552,
      "end": 1738720225552,
      "order": "pre"
    },
    {
      "name": "vite-plugin-vue-devtools",
      "result": "@use 'mixins/mixins' as *;\n\n@include b(aside) {\n  overflow: auto;\n  box-sizing: border-box;\n  flex-shrink: 0;\n  width: var(#{getCssVarName('aside', 'width')}, 300px);\n}\n",
      "start": 1738720225552,
      "end": 1738720225552,
      "order": "pre",
      "sourcemaps": null
    },
    {
      "name": "vite:css",
      "result": "/* Element Chalk Variables */\n.el-aside {\n  overflow: auto;\n  box-sizing: border-box;\n  flex-shrink: 0;\n  width: var(--el-aside-width, 300px);\n}",
      "start": 1738720225552,
      "end": 1738720226102,
      "order": "normal",
      "sourcemaps": {
        "mappings": ""
      }
    },
    {
      "name": "vite:esbuild",
      "start": 1738720226102,
      "end": 1738720226102,
      "order": "normal"
    },
    {
      "name": "vite:json",
      "start": 1738720226102,
      "end": 1738720226102,
      "order": "normal"
    },
    {
      "name": "vite:worker",
      "start": 1738720226102,
      "end": 1738720226102,
      "order": "normal"
    },
    {
      "name": "vite:vue",
      "start": 1738720226104,
      "end": 1738720226104,
      "order": "normal"
    },
    {
      "name": "originjs:commonjs",
      "start": 1738720226105,
      "end": 1738720226105,
      "order": "normal"
    },
    {
      "name": "vite:vue-jsx",
      "start": 1738720226105,
      "end": 1738720226105,
      "order": "normal"
    },
    {
      "name": "inject",
      "start": 1738720226105,
      "end": 1738720226105,
      "order": "normal"
    },
    {
      "name": "vite:define",
      "start": 1738720226105,
      "end": 1738720226105,
      "order": "normal"
    },
    {
      "name": "vite:css-post",
      "result": "import { updateStyle as __vite__updateStyle, removeStyle as __vite__removeStyle } from \"/@vite/client\"\nconst __vite__id = \"E:/lixycode/testcode/node_modules/element-plus/theme-chalk/src/aside.scss\"\nconst __vite__css = \"/* Element Chalk Variables */\\n.el-aside {\\n  overflow: auto;\\n  box-sizing: border-box;\\n  flex-shrink: 0;\\n  width: var(--el-aside-width, 300px);\\n}\"\n__vite__updateStyle(__vite__id, __vite__css)\nimport.meta.hot.accept()\nimport.meta.hot.prune(() => __vite__removeStyle(__vite__id))",
      "start": 1738720226105,
      "end": 1738720226105,
      "order": "normal",
      "sourcemaps": {
        "mappings": ""
      }
    },
    {
      "name": "vite:worker-import-meta-url",
      "start": 1738720226105,
      "end": 1738720226105,
      "order": "normal"
    },
    {
      "name": "vite:asset-import-meta-url",
      "start": 1738720226105,
      "end": 1738720226105,
      "order": "normal"
    },
    {
      "name": "vite:dynamic-import-vars",
      "start": 1738720226105,
      "end": 1738720226105,
      "order": "normal"
    },
    {
      "name": "vite:import-glob",
      "start": 1738720226105,
      "end": 1738720226105,
      "order": "normal"
    },
    {
      "name": "vite-plugin-vue-inspector:post",
      "start": 1738720226105,
      "end": 1738720226105,
      "order": "post"
    },
    {
      "name": "unplugin-auto-import",
      "start": 1738720226105,
      "end": 1738720226105,
      "order": "post"
    },
    {
      "name": "unplugin-vue-components",
      "start": 1738720226105,
      "end": 1738720226105,
      "order": "post"
    },
    {
      "name": "vite:client-inject",
      "start": 1738720226105,
      "end": 1738720226105,
      "order": "normal"
    },
    {
      "name": "vite:css-analysis",
      "start": 1738720226105,
      "end": 1738720226105,
      "order": "normal"
    },
    {
      "name": "vite:import-analysis",
      "result": "import { createHotContext as __vite__createHotContext } from \"/@vite/client\";import.meta.hot = __vite__createHotContext(\"/node_modules/element-plus/theme-chalk/src/aside.scss\");import { updateStyle as __vite__updateStyle, removeStyle as __vite__removeStyle } from \"/@vite/client\"\nconst __vite__id = \"E:/lixycode/testcode/node_modules/element-plus/theme-chalk/src/aside.scss\"\nconst __vite__css = \"/* Element Chalk Variables */\\n.el-aside {\\n  overflow: auto;\\n  box-sizing: border-box;\\n  flex-shrink: 0;\\n  width: var(--el-aside-width, 300px);\\n}\"\n__vite__updateStyle(__vite__id, __vite__css)\nimport.meta.hot.accept()\nimport.meta.hot.prune(() => __vite__removeStyle(__vite__id))",
      "start": 1738720226105,
      "end": 1738720226106,
      "order": "normal",
      "sourcemaps": null
    }
  ]
}
