{
  "resolvedId": "E:/lixycode/testcode/src/views/workflow/FlowDefineUi.vue?vue&type=style&index=0&scoped=d3cdcae2&lang.scss",
  "transforms": [
    {
      "name": "vite:vue",
      "result": "\r\n//todo\r\n",
      "start": 1738721080309,
      "end": 1738721080309,
      "sourcemaps": {
        "version": 3,
        "sources": [
          "E:/lixycode/testcode/src/views/workflow/FlowDefineUi.vue"
        ],
        "names": [],
        "mappings": ";AA8KA,CAAC,CAAC,CAAC,CAAC,CAAC",
        "file": "E:/lixycode/testcode/src/views/workflow/FlowDefineUi.vue",
        "sourceRoot": "",
        "sourcesContent": [
          "<script setup lang=\"ts\">\r\nimport {apiInstance, dialogPreps, dictData} from \"@/api/sh_api\";\r\nimport {ApiUrls} from \"@/components/types/ApiUrls\";\r\nimport {Config} from \"@/api/settings\";\r\nimport {onMounted, provide, reactive, ref, onActivated, onDeactivated, nextTick} from \"vue\";\r\nimport {SearchFields, SelectOption} from \"@/components/types/SearchProps\";\r\nimport {PageFieldInfo, UserFuncInfo} from \"@/components/types/PageFieldInfo\";\r\nimport {getCustomerParam} from \"@/utils/auth\";\r\nimport {useRouter} from \"vue-router\";\r\nimport {useFlowDesign} from \"@/store/FlowDesignStore.ts\";\r\nimport piniaInstance from \"@/store\";\r\nimport {formVisibleTypeList} from \"@/views/workflow/utils/FlowFormUtils.ts\";\r\n\r\ndefineOptions({\r\n  name: 'FlowDefine',\r\n})\r\n//后端交互接口地址\r\nconst dataUrl: ApiUrls = apiInstance(\"flow-engine\", \"workflow/flowDefine\");\r\n//主键\r\nconst primaryKey = \"idFlowDefine\";\r\nconst flowDefineRef = ref();\r\nconst router = useRouter();\r\nconst flowDesign = useFlowDesign(piniaInstance);\r\n//定义表单的所有属性\r\nconst formFields = reactive<Object>({});\r\nprovide(\"formFields\", formFields);\r\nlet flowGroupList = ref<SelectOption[]>([]);\r\nlet flowDeploymentList = ref<SelectOption[]>([\r\n  {name: \"已部署\", \"value\": \"not null\"},\r\n  {name: \"未部署\", \"value\": \"null\"}\r\n]);\r\n//查询属性\r\nconst searchFormData = reactive<SearchFields>({\r\n  \"fieldList\": [\r\n    {\"label\": \"流程名称\", \"fieldName\": \"name\", \"type\": \"input\", matchType: \"lk\", defaultVisible: true},\r\n    {\"label\": \"流程分类\", \"fieldName\": \"flowGroup\", \"type\": \"select\", matchType: \"lk\", defaultVisible: true, optionList: flowGroupList},\r\n    /* {\"label\": \"流程类型\", \"fieldName\": \"flowType\", \"type\": \"input\",matchType:\"lk\",defaultVisible: true},*/\r\n    {\"label\": \"是否部署\", \"fieldName\": \"flowDeploymentId\", \"type\": \"select\", matchType: \"is\", defaultVisible: true, optionList: flowDeploymentList},\r\n  ]\r\n});\r\nconst tableFieldList = reactive<PageFieldInfo | any>({\r\n  \"fieldList\": [\r\n    {\"label\": \"流程名称\", \"fieldName\": \"name\", \"type\": \"input\", \"required\": true, \"formVisible\": true, \"listVisible\": true},\r\n    {\"label\": \"流程部署ID\", \"fieldName\": \"flowDeploymentId\", \"type\": \"input\", \"required\": true, \"formVisible\": true, \"listVisible\": true},\r\n    {\"label\": \"流程分类\", \"fieldName\": \"flowGroup\", \"type\": \"input\", \"required\": false, \"formVisible\": true, \"listVisible\": true},\r\n    {\"label\": \"绑定表单信息\", \"fieldName\": \"bindForm\", \"type\": \"input\", \"required\": false, \"formVisible\": true, \"listVisible\": true},\r\n    {\"label\": \"图标\", \"fieldName\": \"flowIcon\", \"type\": \"input\", \"required\": false, \"formVisible\": true, \"listVisible\": true},\r\n    {\"label\": \"流程类型\", \"fieldName\": \"flowType\", \"type\": \"input\", \"required\": false, \"formVisible\": false, \"listVisible\": false},\r\n    {\"label\": \"流程版本\", \"fieldName\": \"flowVersion\", \"type\": \"input\", \"required\": false, \"formVisible\": true, \"listVisible\": true},\r\n    {\"label\": \"多表单显示模式\", \"fieldName\": \"formVisibleType\", \"type\": \"input\", \"required\": false, \"formVisible\": true, \"listVisible\": true},\r\n    {\"label\": \"流程管理员\", \"fieldName\": \"flowManager\", \"type\": \"input\", \"required\": false, \"formVisible\": true, \"listVisible\": true},\r\n    {\"label\": \"流程Xml文件\", \"fieldName\": \"xmlFile\", \"type\": \"input\", \"required\": true, \"formVisible\": true, \"listVisible\": false},\r\n    {\"label\": \"流程Json文件\", \"fieldName\": \"jsonFile\", \"type\": \"input\", \"required\": true, \"formVisible\": true, \"listVisible\": false},\r\n    {\"label\": \"创建人\", \"fieldName\": \"createdBy\", \"type\": \"input\", \"listVisible\": true, \"preps\": {}, \"commonFlag\": \"Y\"},\r\n    {\"label\": \"修改人\", \"fieldName\": \"updatedBy\", \"type\": \"input\", \"listVisible\": false, \"preps\": {}, \"commonFlag\": \"Y\"},\r\n    {\"label\": \"创建时间\", \"fieldName\": \"createdTime\", \"type\": \"datetime\", \"listVisible\": true, \"preps\": {}, \"commonFlag\": \"Y\"},\r\n    {\"label\": \"修改时间\", \"fieldName\": \"updatedTime\", \"type\": \"datetime\", \"listVisible\": false, \"preps\": {}, \"commonFlag\": \"Y\"},\r\n    {\"label\": \"版本号\", \"fieldName\": \"version\", \"type\": \"number\", \"listVisible\": true, \"preps\": {}, \"commonFlag\": \"Y\"},\r\n    {\"label\": \"是否删除\", \"fieldName\": \"isDel\", \"type\": \"number\", \"listVisible\": false, \"preps\": {}, \"commonFlag\": \"Y\"},\r\n    {\"label\": \"数据编号\", \"fieldName\": \"dataNo\", \"type\": \"input\", \"listVisible\": false, \"preps\": {}, \"commonFlag\": \"Y\"},\r\n    {\"label\": \"状态\", \"fieldName\": \"statusCode\", \"type\": \"select\", \"listVisible\": false, \"preps\": {\"urlOrDictName\": \"common\", \"values\": [], \"name\": \"statusCode\", \"dataSource\": \"dict\", \"props\": {}}, \"commonFlag\": \"Y\"},\r\n    {\"label\": \"状态名称\", \"fieldName\": \"statusName\", \"type\": \"input\", \"listVisible\": false, \"preps\": {}, \"commonFlag\": \"Y\"},\r\n    {\"label\": \"国际编码\", \"fieldName\": \"local\", \"type\": \"input\", \"listVisible\": false, \"preps\": {}, \"commonFlag\": \"Y\"},\r\n    {\"label\": \"备注\", \"fieldName\": \"remark\", \"type\": \"textarea\", \"listVisible\": false, \"preps\": {}, \"commonFlag\": \"Y\"}],\r\n  \"batchFieldList\": [],\r\n  \"userTableFuncs\": [],\r\n  \"dynamicFormas\": [],\r\n  \"orderBy\": [],\r\n  \"batchName\": \"batchDataList\",\r\n  \"tableCellEditabled\": false,\r\n  \"stopAutoLoad\": false\r\n});\r\n//校验\r\nconst rules = {};\r\n//扩展按钮\r\nconst extandBtns = ref<UserFuncInfo[]>([\r\n  {\r\n    icon: \"edit\",\r\n    btnName: \"编辑\",\r\n    priority: 1,\r\n    authority: \"edit\",\r\n    funcName: (row: any) => {\r\n      router.push({path: \"/flowDesign\", query: {data: row[primaryKey]}})\r\n    }\r\n  },\r\n  {\r\n    icon: \"data-view\",\r\n    btnName: \"查看\",\r\n    priority: 2,\r\n    authority: \"view\",\r\n    funcName: (row: any) => {\r\n      router.push({path: \"/flowDesign\", query: {data: row[primaryKey], isView: \"Y\"}})\r\n    }\r\n  }\r\n]);\r\nconst extandBtns2 = ref<UserFuncInfo[]>([\r\n  {\r\n    icon: \"add\",\r\n    btnName: \"新增\",\r\n    authority: \"add\",\r\n    funcName: () => {\r\n      flowDesign.init();\r\n      router.push({path: \"/flowDesign\"})\r\n    }\r\n  },\r\n]);\r\n//控制弹窗相关设置\r\nconst dialogProps = dialogPreps();\r\nprovide(\"dialogProps\", dialogProps);\r\n//初始化方法\r\nconst initData = async () => {\r\n  flowGroupList.value = await dictData(\"flow_group\");\r\n};\r\nconst activated = async () => {\r\n  await nextTick(() => {\r\n    flowDefineRef.value.loadByPage()\r\n  });\r\n}\r\nconst deactivated = () => {\r\n\r\n}\r\n/**\r\n * 列表，查看数据时数据转换\r\n * @param name 名称\r\n * @param cellValue 值\r\n * @param row 列表行数据\r\n */\r\nconst dataFormat = (name: string, cellValue: any, row: any): any => {\r\n  if (name == \"formVisibleType\") {\r\n    return formVisibleTypeList.value.find((item: SelectOption) => item.value == cellValue)?.name || cellValue;\r\n  }\r\n  //转换显示信息\r\n  return cellValue;\r\n}\r\nonMounted(async () => {\r\n  await initData();\r\n});\r\nonActivated(() => {\r\n  activated();\r\n});\r\nonDeactivated(() => {\r\n  deactivated();\r\n});\r\n</script>\r\n<template>\r\n  <star-horse-dialog :isShowBtnContinue=\"true\" :dialog-visible=\"dialogProps.editVisible\" :dialogProps=\"dialogProps\" data-v-inspector=\"src/views/workflow/FlowDefineUi.vue:146:3\">\r\n    <div class=\"dialog-body\" data-v-inspector=\"src/views/workflow/FlowDefineUi.vue:147:5\">\r\n      <star-horse-form @refresh=\"flowDefineRef.loadByPage()\" :compUrl=\"dataUrl\" :fieldList=\"tableFieldList\"\r\n                       :rules=\"rules\" data-v-inspector=\"src/views/workflow/FlowDefineUi.vue:148:7\"/>\r\n    </div>\r\n  </star-horse-dialog>\r\n  <star-horse-dialog :dialog-visible=\"dialogProps.viewVisible\" :dialogProps=\"dialogProps\" :title=\"'查看数据'\"\r\n                     :isView=\"true\" data-v-inspector=\"src/views/workflow/FlowDefineUi.vue:152:3\">\r\n    <div class=\"dialog-body\" data-v-inspector=\"src/views/workflow/FlowDefineUi.vue:154:5\">\r\n      <star-horse-data-view :dataFormat=\"dataFormat\" :field-list=\"tableFieldList\" :compUrl=\"dataUrl\" data-v-inspector=\"src/views/workflow/FlowDefineUi.vue:155:7\"/>\r\n    </div>\r\n  </star-horse-dialog>\r\n  <el-card class=\"inner_content\" data-v-inspector=\"src/views/workflow/FlowDefineUi.vue:158:3\">\r\n    <div class=\"search_btn\" :style=\"{'flex-direction':Config.buttonStyle=='line'?'column':'row'}\" data-v-inspector=\"src/views/workflow/FlowDefineUi.vue:159:5\">\r\n      <star-horse-search-comp @searchData=\"(data)=>flowDefineRef.createSearchParams(data)\" :formData=\"searchFormData\"\r\n                              :compUrl=\"dataUrl\" data-v-inspector=\"src/views/workflow/FlowDefineUi.vue:160:7\"/>\r\n      <hr data-v-inspector=\"src/views/workflow/FlowDefineUi.vue:162:7\"/>\r\n      <star-horse-button-list @tableCompFunc=\"(fun)=>flowDefineRef.tableCompFunc(fun)\" :compUrl=\"dataUrl\"\r\n                              :extand-btns=\"extandBtns2\"\r\n                              :dialogProps=\"dialogProps\" :showType=\"Config.buttonStyle\" data-v-inspector=\"src/views/workflow/FlowDefineUi.vue:163:7\"/>\r\n    </div>\r\n    <hr data-v-inspector=\"src/views/workflow/FlowDefineUi.vue:167:5\"/>\r\n    <star-horse-table-comp ref=\"flowDefineRef\" :fieldList=\"tableFieldList\" :primaryKey=\"primaryKey\"\r\n                           :compUrl=\"dataUrl\"\r\n                           :extand-btns=\"extandBtns\"\r\n                           :dataFormat=\"dataFormat\" data-v-inspector=\"src/views/workflow/FlowDefineUi.vue:168:5\"/>\r\n  </el-card>\r\n</template>\r\n<style lang=\"scss\" scoped>\r\n//todo\r\n</style>\r\n"
        ]
      }
    },
    {
      "name": "vite-plugin-vue-inspector",
      "start": 1738721080309,
      "end": 1738721080309,
      "order": "pre"
    },
    {
      "name": "vite-plugin-vue-devtools",
      "result": "\r\n//todo\r\n",
      "start": 1738721080309,
      "end": 1738721080309,
      "order": "pre",
      "sourcemaps": null
    },
    {
      "name": "vite:css",
      "result": "",
      "start": 1738721080309,
      "end": 1738721080314,
      "order": "normal",
      "sourcemaps": {
        "mappings": ""
      }
    },
    {
      "name": "vite:esbuild",
      "start": 1738721080314,
      "end": 1738721080314,
      "order": "normal"
    },
    {
      "name": "vite:json",
      "start": 1738721080314,
      "end": 1738721080314,
      "order": "normal"
    },
    {
      "name": "vite:worker",
      "start": 1738721080314,
      "end": 1738721080314,
      "order": "normal"
    },
    {
      "name": "vite:vue",
      "result": "",
      "start": 1738721080314,
      "end": 1738721080314,
      "order": "normal",
      "sourcemaps": {
        "mappings": ""
      }
    },
    {
      "name": "originjs:commonjs",
      "start": 1738721080314,
      "end": 1738721080314,
      "order": "normal"
    },
    {
      "name": "vite:vue-jsx",
      "start": 1738721080314,
      "end": 1738721080314,
      "order": "normal"
    },
    {
      "name": "inject",
      "start": 1738721080314,
      "end": 1738721080314,
      "order": "normal"
    },
    {
      "name": "vite:define",
      "start": 1738721080314,
      "end": 1738721080314,
      "order": "normal"
    },
    {
      "name": "vite:css-post",
      "result": "import { updateStyle as __vite__updateStyle, removeStyle as __vite__removeStyle } from \"/@vite/client\"\nconst __vite__id = \"E:/lixycode/testcode/src/views/workflow/FlowDefineUi.vue?vue&type=style&index=0&scoped=d3cdcae2&lang.scss\"\nconst __vite__css = \"\"\n__vite__updateStyle(__vite__id, __vite__css)\nimport.meta.hot.accept()\nimport.meta.hot.prune(() => __vite__removeStyle(__vite__id))",
      "start": 1738721080314,
      "end": 1738721080314,
      "order": "normal",
      "sourcemaps": {
        "mappings": ""
      }
    },
    {
      "name": "vite:worker-import-meta-url",
      "start": 1738721080314,
      "end": 1738721080314,
      "order": "normal"
    },
    {
      "name": "vite:asset-import-meta-url",
      "start": 1738721080314,
      "end": 1738721080314,
      "order": "normal"
    },
    {
      "name": "vite:dynamic-import-vars",
      "start": 1738721080314,
      "end": 1738721080314,
      "order": "normal"
    },
    {
      "name": "vite:import-glob",
      "start": 1738721080314,
      "end": 1738721080314,
      "order": "normal"
    },
    {
      "name": "vite-plugin-vue-inspector:post",
      "start": 1738721080314,
      "end": 1738721080314,
      "order": "post"
    },
    {
      "name": "unplugin-auto-import",
      "start": 1738721080314,
      "end": 1738721080315,
      "order": "post"
    },
    {
      "name": "unplugin-vue-components",
      "result": "/* unplugin-vue-components disabled */import { updateStyle as __vite__updateStyle, removeStyle as __vite__removeStyle } from \"/@vite/client\"\nconst __vite__id = \"E:/lixycode/testcode/src/views/workflow/FlowDefineUi.vue?vue&type=style&index=0&scoped=d3cdcae2&lang.scss\"\nconst __vite__css = \"\"\n__vite__updateStyle(__vite__id, __vite__css)\nimport.meta.hot.accept()\nimport.meta.hot.prune(() => __vite__removeStyle(__vite__id))",
      "start": 1738721080315,
      "end": 1738721080315,
      "order": "post",
      "sourcemaps": {
        "version": 3,
        "sources": [
          "E:/lixycode/testcode/src/views/workflow/FlowDefineUi.vue?vue&type=style&index=0&scoped=d3cdcae2&lang.scss"
        ],
        "sourcesContent": [
          "import { updateStyle as __vite__updateStyle, removeStyle as __vite__removeStyle } from \"/@vite/client\"\nconst __vite__id = \"E:/lixycode/testcode/src/views/workflow/FlowDefineUi.vue?vue&type=style&index=0&scoped=d3cdcae2&lang.scss\"\nconst __vite__css = \"\"\n__vite__updateStyle(__vite__id, __vite__css)\nimport.meta.hot.accept()\nimport.meta.hot.prune(() => __vite__removeStyle(__vite__id))"
        ],
        "names": [],
        "mappings": "sCAAA,MAAM,CAAC,CAAC,CAAC,WAAW,CAAC,EAAE,CAAC,mBAAmB,CAAC,CAAC,WAAW,CAAC,EAAE,CAAC,mBAAmB,CAAC,CAAC,CAAC,IAAI,CAAC,CAAC,CAAC,CAAC,IAAI,CAAC,MAAM;AACrG,KAAK,CAAC,UAAU,CAAC,CAAC,CAAC,CAAC,CAAC,CAAC,CAAC,QAAQ,CAAC,QAAQ,CAAC,GAAG,CAAC,KAAK,CAAC,QAAQ,CAAC,YAAY,CAAC,GAAG,CAAC,GAAG,CAAC,IAAI,CAAC,KAAK,CAAC,KAAK,CAAC,CAAC,CAAC,MAAM,CAAC,QAAQ,CAAC,IAAI,CAAC,IAAI;AAC7H,KAAK,CAAC,WAAW,CAAC,CAAC,CAAC,CAAC;AACrB,mBAAmB,CAAC,UAAU,CAAC,CAAC,WAAW;AAC3C,MAAM,CAAC,IAAI,CAAC,GAAG,CAAC,MAAM,CAAC;AACvB,MAAM,CAAC,IAAI,CAAC,GAAG,CAAC,KAAK,CAAC,CAAC,CAAC,CAAC,CAAC,CAAC,CAAC,mBAAmB,CAAC,UAAU,CAAC"
      }
    },
    {
      "name": "vite:client-inject",
      "start": 1738721080315,
      "end": 1738721080315,
      "order": "normal"
    },
    {
      "name": "vite:css-analysis",
      "start": 1738721080315,
      "end": 1738721080315,
      "order": "normal"
    },
    {
      "name": "vite:import-analysis",
      "result": "import { createHotContext as __vite__createHotContext } from \"/@vite/client\";import.meta.hot = __vite__createHotContext(\"/src/views/workflow/FlowDefineUi.vue?vue&type=style&index=0&scoped=d3cdcae2&lang.scss\");/* unplugin-vue-components disabled */import { updateStyle as __vite__updateStyle, removeStyle as __vite__removeStyle } from \"/@vite/client\"\nconst __vite__id = \"E:/lixycode/testcode/src/views/workflow/FlowDefineUi.vue?vue&type=style&index=0&scoped=d3cdcae2&lang.scss\"\nconst __vite__css = \"\"\n__vite__updateStyle(__vite__id, __vite__css)\nimport.meta.hot.accept()\nimport.meta.hot.prune(() => __vite__removeStyle(__vite__id))",
      "start": 1738721080315,
      "end": 1738721080315,
      "order": "normal",
      "sourcemaps": null
    }
  ]
}
